funmaterial/__init__.py
funmaterial/api/__init__.py
funmaterial/api/pixabay.py
funmaterial/api/unsplash.py
funmaterial/audio/__init__.py
funmaterial/font/__init__.py
funmaterial/font/zenodo.py
funmaterial/picture/__init__.py
funmaterial/schema/__init__.py
funmaterial/schema/base.py
funmaterial/song/__init__.py
funmaterial/song/zenodo.py
funmaterial/video/__init__.py
funmaterial/video/download.py
funmaterial/video/schema.py
funmaterial-1.0.22.dist-info/LICENSE
funmaterial-1.0.22.dist-info/METADATA
funmaterial-1.0.22.dist-info/WHEEL
funmaterial-1.0.22.dist-info/top_level.txt
funmaterial-1.0.22.dist-info/RECORD
