Metadata-Version: 2.1
Name: funmaterial
Version: 1.0.22
Summary: Add your description here
Requires-Python: >=3.8
License-File: LICENSE
Requires-Dist: fundrive>=1.2.60
Requires-Dist: funfake>=1.0.6
Requires-Dist: funget>=1.0.22
Requires-Dist: funsecret>=1.4.29
